api_cat2880_library/__init__.py
api_cat2880_library/config_loader.py
api_cat2880_library/api_client/__init__.py
api_cat2880_library/api_client/api_client.py
api_cat2880_library/api_client/weather_client.py
api_cat2880_library/data_processor/__init__.py
api_cat2880_library/data_processor/data_processor.py
api_cat2880_library-0.2.0.dist-info/METADATA
api_cat2880_library-0.2.0.dist-info/WHEEL
api_cat2880_library-0.2.0.dist-info/top_level.txt
api_cat2880_library-0.2.0.dist-info/RECORD
