Metadata-Version: 2.4
Name: api_cat2880_library
Version: 0.2.0
Summary: A library for making requests to REST APIs with token authentication
Home-page: https://git.e-science.pl/arskar2015_dpp_2025/python_pip.git
Author: arskar2015
Author-email: 276765@student.pwr.edu.pl
Dynamic: author
Dynamic: author-email
Dynamic: description-content-type
Dynamic: home-page
Dynamic: summary
